pakettikauppa/__init__.py
pakettikauppa/merchant.py
pakettikauppa/pakettikauppa.py
pakettikauppa/reseller.py
pakettikauppa-0.1.2.dist-info/DESCRIPTION.rst
pakettikauppa-0.1.2.dist-info/METADATA
pakettikauppa-0.1.2.dist-info/RECORD
pakettikauppa-0.1.2.dist-info/WHEEL
pakettikauppa-0.1.2.dist-info/metadata.json
pakettikauppa-0.1.2.dist-info/top_level.txt
