Metadata-Version: 2.0
Name: pakettikauppa
Version: 0.1.2
Summary: Client python modules for Pakettikauppa integration
Home-page: https://github.com/vilkasgroup/Pakettikauppa
Author: Porntip Chaibamrung
Author-email: tipi@vilkas.fi
License: MIT license
Keywords: pakettikauppa
Platform: UNKNOWN
Classifier: Development Status :: 2 - Pre-Alpha
Classifier: Intended Audience :: Developers
Classifier: License :: OSI Approved :: MIT License
Classifier: Natural Language :: English
Classifier: Programming Language :: Python :: 2.7
Classifier: Programming Language :: Python :: 3.6
Requires-Dist: requests
Requires-Dist: PyYAML
Requires-Dist: cryptography
